{"cameraMode":{"drawMode":0,"name":"Shaded","section":"Shading Mode"},"sceneLighting":false,"audioPlay":false,"sceneViewState":{"showFog":true,"showMaterialUpdate":true,"showSkybox":false,"showFlares":true,"showImageEffects":true,"showParticleSystems":true,"showVisualEffectGraphs":true,"m_FxEnabled":true},"in2DMode":false,"pivot":{"x":26.632884979248048,"y":2.7909116744995119,"z":14.395661354064942},"rotation":{"x":0.018317855894565584,"y":-0.8455200791358948,"z":-0.030052153393626214,"w":-0.5330888032913208},"size":10.0,"orthographic":false}